wfudptools/__init__.py
wfudptools/listener.py
wfudptools/simulator.py
wfudptools-5.3.0.dist-info/WHEEL
wfudptools-5.3.0.dist-info/entry_points.txt
wfudptools-5.3.0.dist-info/LICENSE.txt
wfudptools-5.3.0.dist-info/METADATA
wfudptools-5.3.0.dist-info/RECORD
